python_doten/__init__.py
python_doten/cli.py
python_doten/core.py
python_doten/models.py
python_doten/routines.py
python_doten/data/defaults.json
python_doten/plugins/__init__.py
python_doten/plugins/pomodoro.py
python_doten/plugins/retries.py
python_doten/plugins/workout.py
python_doten-0.1.0.dist-info/licenses/LICENSE
python_doten-0.1.0.dist-info/METADATA
python_doten-0.1.0.dist-info/WHEEL
python_doten-0.1.0.dist-info/entry_points.txt
python_doten-0.1.0.dist-info/top_level.txt
python_doten-0.1.0.dist-info/RECORD
