Metadata-Version: 2.4
Name: python-doten
Version: 0.1.0
Summary: A tiny framework for doing things in sets of ten — reps, retries, batches, and rituals.
Author-email: "Quentin J. Ruff" <quentinjruff@dayrep.com>
Maintainer-email: "Quentin J. Ruff" <quentinjruff@dayrep.com>
License: MIT
Project-URL: Homepage, https://pypi.org/project/python-doten/
Project-URL: Repository, https://pypi.org/project/python-doten/
Project-URL: Issues, https://pypi.org/project/python-doten/
Project-URL: Documentation, https://pypi.org/project/python-doten/
Keywords: productivity,cli,rituals,habits,reps,routines,automation,tasks,batching
Classifier: Development Status :: 3 - Alpha
Classifier: Intended Audience :: End Users/Desktop
Classifier: Intended Audience :: Developers
Classifier: License :: OSI Approved :: MIT License
Classifier: Operating System :: OS Independent
Classifier: Programming Language :: Python
Classifier: Programming Language :: Python :: 3
Classifier: Programming Language :: Python :: 3.9
Classifier: Programming Language :: Python :: 3.10
Classifier: Programming Language :: Python :: 3.11
Classifier: Programming Language :: Python :: 3.12
Classifier: Topic :: Utilities
Classifier: Topic :: Software Development :: Libraries
Classifier: Environment :: Console
Requires-Python: >=3.9
License-File: LICENSE
Requires-Dist: input-output-build
Dynamic: license-file
